pymusicdl_termux/__init__.py
pymusicdl_termux/musicDL.py
pymusicdl_termux/modules/__init__.py
pymusicdl_termux/modules/common.py
pymusicdl_termux/modules/picker.py
pymusicdl_termux/modules/spotify_downloader.py
pymusicdl_termux/modules/ytDownloader.py
pymusicdl_termux-0.1.0.dist-info/LICENSE
pymusicdl_termux-0.1.0.dist-info/METADATA
pymusicdl_termux-0.1.0.dist-info/WHEEL
pymusicdl_termux-0.1.0.dist-info/top_level.txt
pymusicdl_termux-0.1.0.dist-info/RECORD
