Metadata-Version: 2.1
Name: pymusicdl-termux
Version: 0.1.0
Summary: Download spotify and youtube playlists on Termux
Home-page: https://github.com/insaiyancvk/pymusicdl/tree/pymusicdl-termux
Author: C Vamshi Krishna
Author-email: cvamshik1@gmail.com
License: MIT
Keywords: spotify,youtube,music download,music,youtube download,spotify download,termux
Platform: UNKNOWN
Classifier: Development Status :: 5 - Production/Stable
Classifier: Intended Audience :: End Users/Desktop 
Classifier: Topic :: Software Development :: Build Tools
Classifier: License :: OSI Approved :: MIT License
Classifier: Programming Language :: Python :: 3.8
Requires-Dist: pafy
Requires-Dist: pytube
Requires-Dist: requests
Requires-Dist: rich
Requires-Dist: spotipy
Requires-Dist: urllib3
Requires-Dist: youtube-dl
Requires-Dist: youtube-title-parse
